lark_parser_language_server/__init__.py
lark_parser_language_server/__main__.py
lark_parser_language_server/document.py
lark_parser_language_server/formatter.py
lark_parser_language_server/grammars/__init__.py
lark_parser_language_server/grammars/lark.lark
lark_parser_language_server/grammars/lark4ls.lark
lark_parser_language_server/parser.py
lark_parser_language_server/py.typed
lark_parser_language_server/server.py
lark_parser_language_server/symbol_table/__init__.py
lark_parser_language_server/symbol_table/errors.py
lark_parser_language_server/symbol_table/flags.py
lark_parser_language_server/symbol_table/symbol.py
lark_parser_language_server/symbol_table/syntax_tree.py
lark_parser_language_server/symbol_table/validators.py
lark_parser_language_server/syntax_tree/__init__.py
lark_parser_language_server/syntax_tree/nodes.py
lark_parser_language_server/version.py
lark_parser_language_server-0.4.0.dist-info/METADATA
lark_parser_language_server-0.4.0.dist-info/WHEEL
lark_parser_language_server-0.4.0.dist-info/licenses/LICENSE.txt
lark_parser_language_server-0.4.0.dist-info/RECORD
