Metadata-Version: 2.4
Name: lark-parser-language-server
Version: 0.4.0
Summary: Lark Parser Language Server.
License-Expression: Apache-2.0
License-File: LICENSE.txt
Keywords: Dynova,lark,lark parser,lsp,language-server,language-server-protocol
Author: Dynova Development Team
Author-email: dev@dynova.io
Maintainer: zodiacfireworks
Maintainer-email: martin.vuelta@gmail.com
Requires-Python: >=3.9.0,<4.0.0
Classifier: Development Status :: 4 - Beta
Classifier: Intended Audience :: Developers
Classifier: Intended Audience :: Information Technology
Classifier: Intended Audience :: Science/Research
Classifier: License :: OSI Approved :: Apache Software License
Classifier: Programming Language :: Python :: 3.9
Classifier: Programming Language :: Python :: 3.10
Classifier: Programming Language :: Python :: 3.11
Classifier: Programming Language :: Python :: 3.12
Classifier: Programming Language :: Python :: 3.13
Classifier: Topic :: Software Development :: Libraries :: Python Modules
Classifier: Topic :: Software Development :: Interpreters
Classifier: Topic :: Software Development :: Code Generators
Classifier: Topic :: Text Editors :: Integrated Development Environments (IDE)
Classifier: Topic :: Software Development
Classifier: Topic :: System
Classifier: Topic :: Utilities
Classifier: Typing :: Typed
Requires-Dist: lark (>=1.3.0,<2.0.0)
Requires-Dist: pygls (>=1.3.1,<2.0.0)
Project-URL: Bug Tracker, https://github.com/dynovaio/lark-parser-language-server/issues
Project-URL: Changelog, https://github.com/dynovaio/lark-parser-language-server/blob/master/CHANGELOG.md
Project-URL: Documentation, https://dynovaio.github.io/lark-parser-language-server
Project-URL: Download, https://github.com/dynovaio/lark-parser-language-server/archive/refs/tags/v0.4.0.zip
Project-URL: Homepage, https://github.com/dynovaio/lark-parser-language-server
Project-URL: Issues, https://github.com/dynovaio/lark-parser-language-server/issues
Project-URL: Repository, https://github.com/dynovaio/lark-parser-language-server
